babot/__init__.py
babot/cli.py
babot/template/.env.example
babot/template/__init__.py
babot/template/config_base.py
babot/template/main.py
babot/template/requirements.txt
babot/template/ui.py
babot/template/agentes/__init__.py
babot/template/agentes/babot.py
babot/template/config/__init__.py
babot/template/config/babot.yaml
babot/template/herramientas/__init__.py
babot/template/herramientas/utils.py
babot-0.2.6.dist-info/licenses/LICENSE
babot-0.2.6.dist-info/METADATA
babot-0.2.6.dist-info/WHEEL
babot-0.2.6.dist-info/entry_points.txt
babot-0.2.6.dist-info/top_level.txt
babot-0.2.6.dist-info/RECORD
