Metadata-Version: 2.4
Name: babot
Version: 0.2.6
Summary: Framework para crear agentes inteligentes personalizados
Home-page: https://github.com/Excel-ente/babot
Author: Kevin Turkienich
Author-email: kevin_turkienich@outlook.com
Classifier: Programming Language :: Python :: 3
Classifier: License :: OSI Approved :: MIT License
Classifier: Operating System :: OS Independent
Requires-Python: >=3.8
License-File: LICENSE
Requires-Dist: rich>=13.9.0
Requires-Dist: pyyaml>=6.0
Requires-Dist: python-dotenv>=1.0.0
Provides-Extra: agents
Requires-Dist: langchain-ollama>=0.2.2; extra == "agents"
Requires-Dist: pypdf>=5.1.0; extra == "agents"
Requires-Dist: pytesseract>=0.3.13; extra == "agents"
Requires-Dist: pdf2image>=1.17.0; extra == "agents"
Dynamic: author
Dynamic: author-email
Dynamic: classifier
Dynamic: description
Dynamic: description-content-type
Dynamic: home-page
Dynamic: license-file
Dynamic: provides-extra
Dynamic: requires-dist
Dynamic: requires-python
Dynamic: summary
